{
  "tab_enabled": true,
  "tab_name": "tools",
  "tab_stack": { "name": "minecraft:diamond_pickaxe"},
  "tab_items": [
    {
      "name": "fundamentallyfixed:flint_knife"
    },
    {
      "name": "fundamentallyfixed:flint_hatchet"
    },
    {
      "name": "fundamentallyfixed:flint_pick"
    },
    {
      "name": "minecraft:wooden_sword"
    },
    //{
    //  "name": "minecraft:wooden_shovel"
    //},
    {
      "name": "shieldexp:wooden_shield"
    },



    {
      "name": "fundamentallyfixed:copper_knife"
    },
    {
      "name": "fundamentallyfixed:copper_hatchet"
    },
    {
      "name": "fundamentallyfixed:copper_pick"
    },
    {
      "name": "minecraft:leather_helmet"
    },
    {
      "name": "minecraft:leather_chestplate"
    },
    {
      "name": "minecraft:leather_leggings"
    },
    {
      "name": "minecraft:leather_boots"
    },
    {
      "name": "minecraft:leather_horse_armor"
    },


    {
      "name": "fundamentallyfixed:bronze_knife"
    },
    {
      "name": "fundamentallyfixed:bronze_axe"
    },
    {
      "name": "fundamentallyfixed:bronze_pickaxe"
    },
    {
      "name": "fundamentallyfixed:bronze_sword"
    },
    //{
    //  "name": "fundamentallyfixed:bronze_shovel"
    //},
    //{
    //  "name": "fundamentallyfixed:bronze_hoe"
    //},
    {
      "name": "fundamentallyfixed:bronze_hammer"
    },
    {
      "name": "sortilege:bronze_staff"
    },
    {
      "name": "shieldexp:golden_shield"
    },
    {
      "name": "fundamentallyfixed:bronze_helmet"
    },
    {
      "name": "fundamentallyfixed:bronze_chestplate"
    },
    {
      "name": "fundamentallyfixed:bronze_leggings"
    },
    {
      "name": "fundamentallyfixed:bronze_boots"
    },



    {
      "name": "fundamentallyfixed:steel_knife"
    },
    {
      "name": "fundamentallyfixed:steel_axe"
    },
    {
      "name": "fundamentallyfixed:steel_pickaxe"
    },
    {
      "name": "fundamentallyfixed:steel_sword"
    },
    //{
    //  "name": "fundamentallyfixed:steel_shovel"
    //},
    //{
    //  "name": "fundamentallyfixed:steel_hoe"
    //},
    {
      "name": "fundamentallyfixed:steel_hammer"
    },
    {
      "name": "sortilege:steel_staff"
    },
    {
      "name": "shieldexp:iron_shield"
    },
    {
      "name": "fundamentallyfixed:steel_helmet"
    },
    {
      "name": "fundamentallyfixed:steel_chestplate"
    },
    {
      "name": "fundamentallyfixed:steel_leggings"
    },
    {
      "name": "fundamentallyfixed:steel_boots"
    },


    {
      "name": "fundamentallyfixed:diamond_knife"
    },
    {
      "name": "fundamentallyfixed:diamond_axe"
    },
    {
      "name": "fundamentallyfixed:diamond_pickaxe"
    },
    {
      "name": "fundamentallyfixed:diamond_sword"
    },
    //{
    //  "name": "fundamentallyfixed:diamond_shovel"
    //},
    //{
    //  "name": "fundamentallyfixed:diamond_hoe"
    //},
    {
      "name": "fundamentallyfixed:diamond_hammer"
    },
    {
      "name": "sortilege:diamond_staff"
    },
    {
      "name": "shieldexp:diamond_shield"
    },
    {
      "name": "fundamentallyfixed:diamond_helmet"
    },
    {
      "name": "fundamentallyfixed:diamond_chestplate"
    },
    {
      "name": "fundamentallyfixed:diamond_leggings"
    },
    {
      "name": "fundamentallyfixed:diamond_boots"
    },
    {
      "name": "fundamentallyfixed:diamond_horse_armor"
    },


    {
      "name": "fundamentallyfixed:stoldum_knife"
    },
    {
      "name": "fundamentallyfixed:stoldum_axe"
    },
    {
      "name": "fundamentallyfixed:stoldum_pickaxe"
    },
    {
      "name": "fundamentallyfixed:stoldum_sword"
    },
    //{
    //  "name": "modestmining:stoldum_shovel"
    //},
    //{
    //  "name": "modestmining:stoldum_hoe"
    //},
    {
      "name": "fundamentallyfixed:stoldum_hammer"
    },
    {
      "name": "sortilege:stoldum_staff"
    },
    {
      "name": "fundamentallyfixed:stoldum_shield"
    },
    {
      "name": "fundamentallyfixed:stoldum_helmet"
    },
    {
      "name": "fundamentallyfixed:stoldum_chestplate"
    },
    {
      "name": "fundamentallyfixed:stoldum_leggings"
    },
    {
      "name": "fundamentallyfixed:stoldum_boots"
    },


    {
      "name": "fundamentallyfixed:netherite_knife"
    },
    {
      "name": "fundamentallyfixed:netherite_axe"
    },
    {
      "name": "fundamentallyfixed:netherite_pickaxe"
    },
    {
      "name": "fundamentallyfixed:netherite_sword"
    },
    //{
    //  "name": "minecraft:netherite_shovel"
    //},
    //{
    //  "name": "minecraft:netherite_hoe"
    //},
    {
      "name": "fundamentallyfixed:netherite_hammer"
    },
    {
      "name": "sortilege:netherite_staff"
    },
    {
      "name": "shieldexp:netherite_shield"
    },
    {
      "name": "fundamentallyfixed:netherite_helmet"
    },
    {
      "name": "fundamentallyfixed:netherite_chestplate"
    },
    {
      "name": "fundamentallyfixed:netherite_leggings"
    },
    {
      "name": "fundamentallyfixed:netherite_boots"
    },


    {
      "name": "fundamentallyfixed:prismarite_knife"
    },
    {
      "name": "fundamentallyfixed:prismarite_axe"
    },
    {
      "name": "fundamentallyfixed:prismarite_pickaxe"
    },
    {
      "name": "fundamentallyfixed:prismarite_sword"
    },
    //{
    //  "name": "modestmining:prismarite_shovel"
    //},
    //{
    //  "name": "modestmining:prismarite_hoe"
    //},
    {
      "name": "fundamentallyfixed:prismarite_hammer"
    },
    {
      "name": "sortilege:prismarite_staff"
    },
    {
      "name": "fundamentallyfixed:prismarite_shield"
    },
    {
      "name": "fundamentallyfixed:prismarite_helmet"
    },
    {
      "name": "fundamentallyfixed:prismarite_chestplate"
    },
    {
      "name": "fundamentallyfixed:prismarite_leggings"
    },
    {
      "name": "fundamentallyfixed:prismarite_boots"
    },


    {
      "name": "fundamentallyfixed:electrum_knife"
    },
    {
      "name": "fundamentallyfixed:electrum_axe"
    },
    {
      "name": "fundamentallyfixed:electrum_pickaxe"
    },
    {
      "name": "fundamentallyfixed:electrum_sword"
    },
    //{
    //  "name": "fundamentallyfixed:electrum_shovel"
    //},
    //{
    //  "name": "fundamentallyfixed:electrum_hoe"
    //},
    {
      "name": "fundamentallyfixed:electrum_hammer"
    },
    {
      "name": "sortilege:electrum_staff"
    },
    {
      "name": "shieldexp:electrum_shield"
    },
    {
      "name": "fundamentallyfixed:electrum_helmet"
    },
    {
      "name": "fundamentallyfixed:electrum_chestplate"
    },
    {
      "name": "fundamentallyfixed:electrum_leggings"
    },
    {
      "name": "fundamentallyfixed:electrum_boots"
    },


    {
      "name": "fundamentallyfixed:chlorophite_knife"
    },
    {
      "name": "fundamentallyfixed:chlorophite_axe"
    },
    {
      "name": "fundamentallyfixed:chlorophite_pickaxe"
    },
    {
      "name": "fundamentallyfixed:chlorophite_sword"
    },
    //{
    //  "name": "modestmining:chlorophite_shovel"
    //},
    //{
    //  "name": "modestmining:chlorophite_hoe"
    //},
    {
      "name": "fundamentallyfixed:chlorophite_hammer"
    },
    {
      "name": "sortilege:chlorophite_staff"
    },
    {
      "name": "fundamentallyfixed:chlorophite_shield"
    },
    {
      "name": "fundamentallyfixed:chlorophite_helmet"
    },
    {
      "name": "fundamentallyfixed:chlorophite_chestplate"
    },
    {
      "name": "fundamentallyfixed:chlorophite_leggings"
    },
    {
      "name": "fundamentallyfixed:chlorophite_boots"
    },


    {
      "name": "fundamentallyfixed:mythril_knife"
    },
    {
      "name": "fundamentallyfixed:mythril_axe"
    },
    {
      "name": "fundamentallyfixed:mythril_pickaxe"
    },
    {
      "name": "fundamentallyfixed:mythril_sword"
    },
    //{
    //  "name": "modestmining:mythril_shovel"
    //},
    //{
    //  "name": "modestmining:mythril_hoe"
    //},
    {
      "name": "fundamentallyfixed:mythril_hammer"
    },
    {
      "name": "sortilege:mythril_staff"
    },
    {
      "name": "fundamentallyfixed:mythril_shield"
    },
    {
      "name": "fundamentallyfixed:mythril_helmet"
    },
    {
      "name": "fundamentallyfixed:mythril_chestplate"
    },
    {
      "name": "fundamentallyfixed:mythril_leggings"
    },
    {
      "name": "fundamentallyfixed:mythril_boots"
    },


    {
      "name": "fundamentallyfixed:hallowed_knife"
    },
    {
      "name": "fundamentallyfixed:hallowed_axe"
    },
    {
      "name": "fundamentallyfixed:hallowed_pickaxe"
    },
    {
      "name": "fundamentallyfixed:hallowed_sword"
    },
    //{
    //  "name": "modestmining:hallowed_shovel"
    //},
    //{
    //  "name": "modestmining:hallowed_hoe"
    //},
    {
      "name": "fundamentallyfixed:hallowed_hammer"
    },
    {
      "name": "sortilege:hallowed_staff"
    },
    {
      "name": "fundamentallyfixed:hallowed_shield"
    },
    {
      "name": "fundamentallyfixed:hallowed_helmet"
    },
    {
      "name": "fundamentallyfixed:hallowed_chestplate"
    },
    {
      "name": "fundamentallyfixed:hallowed_leggings"
    },
    {
      "name": "fundamentallyfixed:hallowed_boots"
    },


    {
      "name": "fundamentallyfixed:gravitite_knife"
    },
    {
      "name": "fundamentallyfixed:gravitite_axe"
    },
    {
      "name": "fundamentallyfixed:gravitite_pickaxe"
    },
    {
      "name": "fundamentallyfixed:gravitite_sword"
    },
    //{
    //  "name": "modestmining:gravitite_shovel"
    //},
    //{
    //  "name": "modestmining:gravitite_hoe"
    //},
    {
      "name": "fundamentallyfixed:gravitite_hammer"
    },
    {
      "name": "sortilege:gravitite_staff"
    },
    {
      "name": "fundamentallyfixed:gravitite_shield"
    },
    {
      "name": "fundamentallyfixed:gravitite_helmet"
    },
    {
      "name": "fundamentallyfixed:gravitite_chestplate"
    },
    {
      "name": "fundamentallyfixed:gravitite_leggings"
    },
    {
      "name": "fundamentallyfixed:gravitite_boots"
    },


    {
      "name": "fundamentallyfixed:voidendum_knife"
    },
    {
      "name": "fundamentallyfixed:voidendum_axe"
    },
    {
      "name": "fundamentallyfixed:voidendum_pickaxe"
    },
    {
      "name": "fundamentallyfixed:voidendum_sword"
    },
    //{
    //  "name": "modestmining:voidendum_shovel"
    //},
    //{
    //  "name": "modestmining:voidendum_hoe"
    //},
    {
      "name": "fundamentallyfixed:voidendum_hammer"
    },
    {
      "name": "sortilege:voidendum_staff"
    },
    {
      "name": "fundamentallyfixed:voidendum_shield"
    },
    {
      "name": "fundamentallyfixed:voidendum_helmet"
    },
    {
      "name": "fundamentallyfixed:voidendum_chestplate"
    },
    {
      "name": "fundamentallyfixed:voidendum_leggings"
    },
    {
      "name": "fundamentallyfixed:voidendum_boots"
    },


    //{
    //  "name": "sullysmod:jade_shield"
    //},
    //{
    //  "name": "minecraft:turtle_helmet"
    //},
    //{
    //  "name": "alexsmobs:crocodile_chestplate"
    //},
    //{
    //  "name": "alexsmobs:flying_fish_boots"
    //},
    //{
    //  "name": "alexsmobs:frontier_cap"
    //},
    //{
    //  "name": "autumnity:snail_shell_chestplate"
    //},
    //{
    //  "name": "environmental:yak_pants"
    //},
    //{
    //  "name": "windswept:snow_boots"
    //},
    //{
    //  "name": "savage_and_ravage:mask_of_dishonesty"
    //},
    {
      "name": "alexsmobs:rocky_chestplate"
    },
    //{
    //  "name": "alexsmobs:centipede_leggings"
    //},
    //{
    //  "name": "alexsmobs:roadrunner_boots"
    //},
    {
      "name": "alexsmobs:fedora"
    },
    {
      "name": "minecraft:elytra"
    },
    //{
    //  "name": "alexsmobs:emu_leggings"
    //},
    {
      "name": "minecraft:shulker_shell"
    },
    //{
    //  "name": "quark:backpack"
    //},


    //{
    //  "name": "savage_and_ravage:cleaver_of_beheading"
    //},
    //{
    //  "name": "minecraft:trident"
    //},
    {
      "name": "supplementaries:quiver"
    },
    {
      "name": "minecraft:bow"
    },
    {
      "name": "minecraft:crossbow"
    },
    {
      "name": "alexsmobs:squid_grapple"
    },
    {
      "name": "supplementaries:slingshot"
    },
    {
      "name": "minecraft:fishing_rod"
    },
    {
      "name": "minecraft:carrot_on_a_stick"
    },
    {
      "name": "minecraft:warped_fungus_on_a_stick"
    },
    {
      "name": "quark:trowel"
    },
    {
      "name": "minecraft:flint_and_steel"
    },
    {
      "name": "modestmining:brush"
    },
    {
      "name": "modestmining:chisel"
    },
    {
      "name": "davespotioneering:white_umbrella"
    },
    {
      "name": "davespotioneering:pink_umbrella"
    },
    {
      "name": "davespotioneering:magenta_umbrella"
    },
    {
      "name": "davespotioneering:purple_umbrella"
    },
    {
      "name": "davespotioneering:blue_umbrella"
    },
    {
      "name": "davespotioneering:light_blue_umbrella"
    },
    {
      "name": "davespotioneering:cyan_umbrella"
    },
    {
      "name": "davespotioneering:green_umbrella"
    },
    {
      "name": "davespotioneering:lime_umbrella"
    },
    {
      "name": "davespotioneering:yellow_umbrella"
    },
    {
      "name": "davespotioneering:orange_umbrella"
    },
    {
      "name": "davespotioneering:red_umbrella"
    },
    {
      "name": "davespotioneering:brown_umbrella"
    },
    {
      "name": "davespotioneering:black_umbrella"
    },
    {
      "name": "davespotioneering:gray_umbrella"
    },
    {
      "name": "davespotioneering:light_gray_umbrella"
    },
    //{
    //   "name": "create:wrench"
    //},
    {
      "name": "quark:echorang"
    },
    {
      "name": "spelunkery:echo_fork"
    },


    {
      "name": "windswept:wooden_bucket"
    },
    {
      "name": "minecraft:bucket"
    },
    {
      "name": "minecraft:clock"
    },
    {
      "name": "spelunkery:depth_gauge"
    },
    {
      "name": "minecraft:compass"
    },
    {
      "name": "spelunkery:magnetic_compass"
    },
    {
      "name": "alexsmobs:echolocator"
    },
    {
      "name": "minecraft:recovery_compass"
    },
    {
      "name": "quark:abacus"
    },
    {
      "name": "spelunkery:item_magnet"
    },
    {
      "name": "heartstone:heartstone"
    },
    {
      "name": "oreganized:silver_mirror"
    },
    {
      "name": "spelunkery:nephrite_charm"
    },
    {
      "name": "savage_and_ravage:conch_of_conjuring"
    },
    {
      "name": "minecraft:totem_of_undying"
    },
    //{
    //  "name": "pet_cemetery:pet_collar"
    //},
    {
      "name": "supplementaries:bomb"
    },
    {
      "name": "supplementaries:bomb_blue"
    },
    {
      "name": "supplementaries:bomb_spiky"
    },
    {
      "name": "spelunkery:mineomite"
    },
    {
      "name": "alexsmobs:straddleboard"
    },
    {
      "name": "minecraft:saddle"
    },
    {
      "name": "alexsmobs:straddle_saddle"
    },
    {
      "name": "alexsmobs:straddle_helmet"
    },
    {
      "name": "supplementaries:flute"
    },
    //{
    //  "name": "alexsmobs:pigshoes"
    //},


    {
      "name": "minecraft:lead"
    },
    {
      "name": "alexsmobs:vine_lasso"
    },
    {
      "name": "minecraft:name_tag"
    },
    {
      "name": "minecraft:goat_horn"
    },
    {
      "name": "minecraft:spyglass"
    },
    {
      "name": "minecraft:bundle"
    },
    {
      "name": "quark:seed_pouch"
    },
    {
      "name": "supplementaries:key"
    },
    {
      "name": "quark:bottled_cloud"
    },


    {
      "name": "xercamusic:flute"
    },
    {
      "name": "xercamusic:banjo"
    },
    {
      "name": "xercamusic:guitar"
    },
    {
      "name": "xercamusic:xylophone"
    },
    {
      "name": "xercamusic:sansula"
    },
    {
      "name": "xercamusic:drum"
    },
    {
      "name": "xercamusic:xylophone"
    },
    {
      "name": "xercamusic:cello"
    },
    {
      "name": "xercamusic:violin"
    },
    {
      "name": "xercamusic:saxophone"
    },
    {
      "name": "xercamusic:cymbal"
    },
    {
      "name": "xercamusic:french_horn"
    },
    {
      "name": "xercamusic:oboe"
    },
    {
      "name": "xercamusic:lyre"
    },
    {
      "name": "xercamusic:tubular_bell"
    },
    {
      "name": "xercamusic:god"
    },
    {
      "name": "xercamusic:bass_guitar"
    },
    {
      "name": "xercamusic:redstone_guitar"
    },


    {
      "name": "minecraft:arrow"
    },
    {
      "name": "minecraft:torch_arrow"
    },
    {
      "name": "neapolitan:bananarrow"
    },
    {
      "name": "savage_and_ravage:mischief_arrow"
    },
    {
      "name": "alexsmobs:shark_tooth_arrow"
    },
    {
      "name": "supplementaries:rope_arrow"
    },
    {
      "name": "minecraft:spectral_arrow"
    },
    {
      "name": "minecraft:map"
    },
    {
      "name": "minecraft:filled_map"
    },
    {
      "name": "minecraft:writable_book"
    },
    {
      "name": "minecraft:written_book"
    },
    {
      "name": "minecraft:knowledge_book"
    },
    {
      "name": "minecraft:enchanted_book"
    },
    {
      "name": "quark:ancient_tome"
    },
    {
      "name": "minecraft:debug_stick"
    }
  ]
}
